{"nKupOdu4Keb7Y3ftXOV5Tw==":"illust_57794715_20180526-171955-1466x1100.png","jPBy7S4PtlK9AfmiwGSSeA==":"illust_57794715_20180526-171956-1466x1100.png","t7sMtZzcPzgpytxpbJJ7qg==":"illust_57794715_20180526-171957-1466x1100.png","6fbS8vKT6/oJ3nbZOMHVag==":"515e3867124237.5b2e9fc4c21b7-2000x1132.png","XxVjagIsh/lA8Yyrtn3siA==":"980c7a67124365.5b2ea103aa3c0-1332x749.png","eXC6rgcJavjvkUoHsWOuzw==":"illust_59322853_20180526-171902-122x122.png","XCMg/glzTbAwXoo88bFOew==":"symbol%20firefox-122x117.png","Z3owNRpqQumw98xu8plYLA==":"mossawi_226238914765_20170515131921-9641794022-1920x1080.png","ajuGP/BKalH5AC0h8bBs6g==":"nissan_skyline-2220x1249.png","xjWhMkPsMppjoym/cU8L9g==":"darling%20in%20the%20franxx-2000x3556.png","WQ0HOKEbLzRymF5Gw6Xn5w==":"darling%20in%20the%20franxx-2000x3556.png","0g2GLC94VQSlPlwfV+Dnvg==":"imagine__1___cs_go___wallpaper_by_pixarua-dbzojqu-2000x1125.png","9q2Z0J6FrZLF5lypt9AslQ==":"batmobile-1920x1080.png","cEUQmTMZOCkVDt5eU486Zw==":"batmobile-1-1920x1080.png","XSOIhmgJPgngG8s2R4+mdA==":"batmobile-2-1920x1080.png","NO6TO5IYTg0Hay3KCDJZ6g==":"batmobile-3-1920x1080.png","G0RtKrIDO5FwJnBvKIawtA==":"nissan_skyline-2000x1125.png","/DYPcoZGHS3tyrc0+2zpLQ==":"980c7a67124365.5b2ea103aa3c0-2000x1125.png","Drhl4nrRWtXJTXWketsinw==":"3e167367142985.5b2fa69970fd7-2000x3556.png","8Gu0rVbJXUk3Ws+Ol8hcXw==":"3e167367142985.5b2fa69970fd7-1-2000x3556.png","5uQJ6ehYk1//sA+Yw1WgiA==":"3e167367142985.5b2fa69970fd7-2-2000x3556.png","ReujUyV0M9T/+9EJiwZlzw==":"14723973559249-510x510.jpg","vznBrrSsVHJNBUdLl3traA==":"2338031_tide_logo_rgb-2014-510x510.jpg","Zt4uNlkQZQSnMVmB6E47rw==":"cmqy4xy8_400x400-400x400.png","Q7GS0wnBQgxzY/XzrtiP4w==":"kotatsu%20fischzball%202-510x510.png","ofIiwYPWURbG07RPPqahDQ==":"waffle-256x256.png","Mm0LXG+S0H7Gvjcd0dq+Rg==":"jkqrdkj9_400x400-400x400.jpg","51XyJ9EeuR36VrR2odcRlg==":"productions-1200x670.jpg","zBqvv8td4i3xoowBmZSM0w==":"sony-18-110mm-review-2-1920x1080.jpg","3XQ5GdBm7G0zjQVtXLLhbw==":"0000881_counter-strike-global-offensive-450-362x450.jpg","JoKEXsY4lg8u/9bI07vdNg==":"header-460x215.jpg","68EBkFo2pqkJyje86nXF5A==":"header%20(1)-460x215.jpg","8VbJKYO1YKqTz0uBrdFMnw==":"header%20(2)-460x215.jpg","gUwZ93YZ5laqqeKNr4tv0Q==":"header_alt_assets-2-460x215.jpg","+O+we7tytHBWWulOhybPTg==":"sony-18-110mm-review-3-1920x1080.jpg","5MzlVoatYf+4R7+lY9bksw==":"sony-18-110mm-review-4-1920x1080.jpg","1Bp3tsAFV0uryydJg/kFVA==":"header%20(3)-460x215.jpg","1mB77FGbAJqrUeeCoHggZg==":"header%20(4)-460x215.jpg","z0vnTWoAtcoXv/5NO4NdCg==":"header%20(5)-460x215.jpg","lM6wXKydJ/qEn2q4+qrETw==":"header%20(6)-460x215.jpg","xArvkJZrfZsMmNH+kignKA==":"twitter_logo_bird_transparent_png-3360x2728.png","tyOkZHOpSRgW8/cj8LdrPA==":"515e3867124237.5b2e9fc4c21b7-1-2000x1132.png"}